yamlfield/__init__.py
yamlfield/apps.py
yamlfield/fields.py
django_ruamel_yamlfield-0.1.2.dist-info/LICENSE
django_ruamel_yamlfield-0.1.2.dist-info/METADATA
django_ruamel_yamlfield-0.1.2.dist-info/WHEEL
django_ruamel_yamlfield-0.1.2.dist-info/top_level.txt
django_ruamel_yamlfield-0.1.2.dist-info/RECORD
